myweb/__init__.py
myweb/app.py
myweb/templates/__init__.py
myweb/templates/form.html
myweb/templates/home.html
myweb-0.0.2.dist-info/METADATA
myweb-0.0.2.dist-info/RECORD
myweb-0.0.2.dist-info/WHEEL
myweb-0.0.2.dist-info/top_level.txt
